dbt_serverless/__init__.py
dbt_serverless/config/__init__.py
dbt_serverless/config/logging.yml
dbt_serverless/lib/__init__.py
dbt_serverless/lib/file_helpers.py
dbt_serverless/lib/subprocess_helpers.py
dbt_serverless/main.py
dbt_serverless-0.1.2.dist-info/LICENSE.txt
dbt_serverless-0.1.2.dist-info/WHEEL
dbt_serverless-0.1.2.dist-info/METADATA
dbt_serverless-0.1.2.dist-info/RECORD
