Metadata-Version: 2.1
Name: dbt-serverless
Version: 0.1.2
Summary: Project to deploy dbt as a serverless application in Cloud Run
Home-page: https://github.com/JeremyLG/dbt-serverless
License: MIT
Author: JeremyLG
Author-email: jeremy.le-gall@hotmail.fr
Requires-Python: >=3.9,<3.11
Classifier: Development Status :: 2 - Pre-Alpha
Classifier: Intended Audience :: Developers
Classifier: License :: OSI Approved :: MIT License
Classifier: Operating System :: OS Independent
Classifier: Programming Language :: Python
Classifier: Programming Language :: Python :: 3
Classifier: Programming Language :: Python :: 3.9
Classifier: Programming Language :: Python :: 3.10
Classifier: Programming Language :: Python :: 3
Classifier: Programming Language :: Python :: 3 :: Only
Classifier: Programming Language :: Python :: 3.10
Classifier: Programming Language :: Python :: 3.9
Classifier: Typing :: Typed
Requires-Dist: PyYAML (>=6.0,<7.0)
Requires-Dist: dbt-bigquery (>=1.3.0,<2.0.0)
Requires-Dist: fastapi (>=0.89.0,<0.90.0)
Requires-Dist: google-cloud-storage (>=2.7.0,<3.0.0)
Requires-Dist: pulumi (==3.33.1)
Requires-Dist: pulumi-gcp (>=6.46.0,<7.0.0)
Requires-Dist: pydantic (>=1.10.4,<2.0.0)
Requires-Dist: uvicorn (>=0.20.0,<0.21.0)
Project-URL: Documentation, https://JeremyLG.github.io/dbt-serverless/
Project-URL: Repository, https://github.com/JeremyLG/dbt-serverless
